ipyspin/__init__.py
ipyspin/_frontend.py
ipyspin/_version.py
ipyspin/spin.py
ipyspin/labextension/package.json
ipyspin/labextension/static/35.f9e3cf4393f130f192d2.js
ipyspin/labextension/static/480.a8f2f9ea280556f366f2.js
ipyspin/labextension/static/568.8144814634d014162d93.js
ipyspin/labextension/static/remoteEntry.3f91aec877f8ac0c4b3e.js
ipyspin/labextension/static/style.js
ipyspin/labextension/static/third-party-licenses.json
ipyspin/nbextension/__init__.py
ipyspin/nbextension/static/extension.js
ipyspin/nbextension/static/index.js
ipyspin/nbextension/static/index.js.map
ipyspin-1.0.1.data/data/etc/jupyter/nbconfig/notebook.d/ipyspin.json
ipyspin-1.0.1.data/data/share/jupyter/labextensions/ipyspin/package.json
ipyspin-1.0.1.data/data/share/jupyter/labextensions/ipyspin/static/35.f9e3cf4393f130f192d2.js
ipyspin-1.0.1.data/data/share/jupyter/labextensions/ipyspin/static/480.a8f2f9ea280556f366f2.js
ipyspin-1.0.1.data/data/share/jupyter/labextensions/ipyspin/static/568.8144814634d014162d93.js
ipyspin-1.0.1.data/data/share/jupyter/labextensions/ipyspin/static/remoteEntry.3f91aec877f8ac0c4b3e.js
ipyspin-1.0.1.data/data/share/jupyter/labextensions/ipyspin/static/style.js
ipyspin-1.0.1.data/data/share/jupyter/labextensions/ipyspin/static/third-party-licenses.json
ipyspin-1.0.1.data/data/share/jupyter/nbextensions/ipyspin/extension.js
ipyspin-1.0.1.data/data/share/jupyter/nbextensions/ipyspin/index.js
ipyspin-1.0.1.data/data/share/jupyter/nbextensions/ipyspin/index.js.map
ipyspin-1.0.1.dist-info/LICENSE.txt
ipyspin-1.0.1.dist-info/METADATA
ipyspin-1.0.1.dist-info/WHEEL
ipyspin-1.0.1.dist-info/top_level.txt
ipyspin-1.0.1.dist-info/RECORD
