Metadata-Version: 2.1
Name: ipyspin
Version: 1.0.1
Summary: A Jupyter widget library for dynamically creating spinning activity indicators
Home-page: https://github.com/davidbrochart/ipyspin
Author: David Brochart
Author-email: david.brochart@gmail.com
Keywords: ipython,jupyter,widgets
Classifier: Development Status :: 4 - Beta
Classifier: Framework :: IPython
Classifier: Intended Audience :: Developers
Classifier: Intended Audience :: Science/Research
Classifier: Topic :: Multimedia :: Graphics
Classifier: Programming Language :: Python :: 3.6
Classifier: Programming Language :: Python :: 3.7
Classifier: Programming Language :: Python :: 3.8
Classifier: Programming Language :: Python :: 3.9
License-File: LICENSE.txt
Requires-Dist: ipywidgets (<9,>=7.6.0)
